cfake/fake.py
cfake/idno_gen.py
cfake-0.1.202208171026.dist-info/LICENSE
cfake-0.1.202208171026.dist-info/METADATA
cfake-0.1.202208171026.dist-info/WHEEL
cfake-0.1.202208171026.dist-info/entry_points.txt
cfake-0.1.202208171026.dist-info/top_level.txt
cfake-0.1.202208171026.dist-info/RECORD
