Metadata-Version: 2.1
Name: cfake
Version: 0.1.202208171026
Summary: 一个简单的测试数据生成器
Author: hammer
Author-email: liuzhuogood@foxmail.com
License-File: LICENSE
